{
  "$id": "/schemas/v1/core/tasks-get-request.json",
  "$schema": "http://json-schema.org/draft-07/schema#",
  "additionalProperties": false,
  "description": "Request parameters for retrieving a specific task by ID with optional conversation history across all AdCP domains",
  "examples": [
    {
      "data": {
        "task_id": "task_456"
      },
      "description": "Check task status"
    },
    {
      "data": {
        "include_history": true,
        "task_id": "task_123"
      },
      "description": "Get task with full conversation history"
    }
  ],
  "properties": {
    "context": {
      "additionalProperties": true,
      "description": "Initiator-provided context included in the request payload. Agents must echo this value back unchanged in responses and webhooks. Use for UI/session hints, correlation tokens, or tracking metadata.",
      "type": "object"
    },
    "include_history": {
      "default": false,
      "description": "Include full conversation history for this task (may increase response size)",
      "type": "boolean"
    },
    "task_id": {
      "description": "Unique identifier of the task to retrieve",
      "type": "string"
    }
  },
  "required": [
    "task_id"
  ],
  "title": "Tasks Get Request",
  "type": "object"
}